data_analysis_cwo/__init__.py
data_analysis_cwo/_plot_from_subfolders_until_user_terminate.py
data_analysis_cwo/_plot_only_user_requested_column.py
data_analysis_cwo/main.py
data_analysis_cwo-6.0.0.dist-info/LICENSE
data_analysis_cwo-6.0.0.dist-info/METADATA
data_analysis_cwo-6.0.0.dist-info/WHEEL
data_analysis_cwo-6.0.0.dist-info/entry_points.txt
data_analysis_cwo-6.0.0.dist-info/top_level.txt
data_analysis_cwo-6.0.0.dist-info/RECORD
